[{"userUsername":"a","userPassword":"a","userPastTransactions":[],"userShoppingCart":[],"userCurrentTransactions":[],"userLastName":"ff","userRewardsPoints":0,"userFirstName":"ff","userBirthday":"7-8-88"},{"userUsername":"f","userPassword":"a","userPastTransactions":[],"userShoppingCart":[],"userCurrentTransactions":[],"userLastName":"smith","userRewardsPoints":0,"userFirstName":"fran","userBirthday":"3-4-44"},{"userUsername":"v","userPassword":"v","userPastTransactions":[],"userShoppingCart":[],"userCurrentTransactions":[],"userLastName":"Jones","userRewardsPoints":0,"userFirstName":"Greg ","userBirthday":"3-6-66"}]